{
  "fileFormatID": 1891,
  "formatName": "Hangul Word Processor Document",
  "version": "3",
  "formatDescription": "Hangul is a Word Processor application created by South Korean software company Hancom. HWP is the native format. A link to the file format specification can be found here: https://www.hancom.com/etc/hwpDownload.do",
  "releaseDate": null,
  "withdrawnDate": null,
  "binaryFileFormat": null,
  "formatNote": null,
  "lastUpdatedDate": "18 Aug 2017",
  "formatSourceID": 1,
  "provenanceCompoundName": "Digital Preservation Department / The National Archives",
  "formatProvenance": null,
  "formatSourceDate": "18 Aug 2017",
  "formatDisclosure": null,
  "formatEnvironment": null,
  "formatRisk": null,
  "formatAliases": null,
  "formatTypes": "Word Processor",
  "byteOrders": null,
  "formatFamilies": null,
  "identifiers": [
    {
      "identifierText": "fmt/1083",
      "identifierType": "PUID"
    }
  ],
  "internalSignatures": [
    {
      "signatureID": 1464,
      "positionType": "Absolute from BOF",
      "offset": 0,
      "maxOffset": 0,
      "byteSequence": "48575020446F63756D656E742046696C652056332E3030201A0102030405",
      "endianness": null,
      "name": "HWP 3",
      "note": "BOF: \"HWP Document File V3.00 \" 0x1A0102030405\r\nhttps://www.hancom.com/etc/hwpDownload.do"
    }
  ],
  "externalSignatures": [
    {
      "externalSignature": "hwp",
      "signatureType": "File extension"
    }
  ],
  "relationships": [],
  "source": 1
}