{
  "fileFormatID": 3946,
  "formatName": "WOZ Disk Image File",
  "provenanceCompoundName": "Brigham Young University / Brigham Young University",
  "identifiers": [
    {
      "identifierText": "fmt/2059",
      "identifierType": "PUID"
    }
  ],
  "internalSignatures": [
    {
      "signatureID": 3422,
      "name": "WOZ Disk Image File",
      "note": "",
      "byteSequences": [
        {
          "positionType": "Absolute from BOF",
          "offset": 0,
          "maxOffset": 0,
          "byteSequence": "574F5A31FF0A0D0A",
          "endianness": null
        }
      ]
    }
  ],
  "externalSignatures": [
    {
      "externalSignature": "woz",
      "signatureType": "File extension"
    }
  ],
  "relationships": [],
  "source": 299
}